jzai/__init__.py
jzai/bot.py
jzai/cli.py
jzai-59.84.7.dist-info/LICENCE
jzai-59.84.7.dist-info/METADATA
jzai-59.84.7.dist-info/WHEEL
jzai-59.84.7.dist-info/entry_points.txt
jzai-59.84.7.dist-info/top_level.txt
jzai-59.84.7.dist-info/RECORD
