Metadata-Version: 2.1
Name: jzai
Version: 59.84.7
Summary: Next Gen AI Bot
Home-page: https://github.com/Webiluxe-Creations/jzai
Author: Zack Allen
Author-email: zjacka01@sfx.act.edu.au
License: MIT
Keywords: AI,Bot,GPT
Classifier: Programming Language :: Python :: 3
Classifier: License :: OSI Approved :: MIT License
Classifier: Operating System :: OS Independent
License-File: LICENCE
Requires-Dist: nltk
Requires-Dist: textblob
Requires-Dist: click
Requires-Dist: requests
Requires-Dist: setuptools
Requires-Dist: cryptography
